[{"Id":22,"Group":1,"Item":33916,"Amount":1998,"Enabled":true,"Type":"Purchase","AmountMode":"Restock"},{"Group":2,"Item":12669,"Amount":999,"Enabled":true,"Type":"Exchange","AmountMode":"Restock"},{"Id":1,"Group":2,"Item":41780,"Amount":70,"Enabled":true,"Type":"Exchange","AmountMode":"Restock"},{"Id":15,"Group":2,"Item":16911,"Amount":600,"Enabled":true,"Type":"Alchemist","Hq":true,"AmountMode":"Restock"},{"Id":2,"Group":3,"Item":41780,"Amount":140,"Enabled":true,"Type":"Exchange","AmountMode":"Restock"},{"Id":16,"Group":3,"Item":12669,"Amount":1299,"Enabled":true,"Type":"Exchange","AmountMode":"Restock"},{"Id":17,"Group":3,"Item":16911,"Amount":1200,"Enabled":true,"Type":"Alchemist","Hq":true,"AmountMode":"Restock"},{"Id":3,"Group":4,"Item":41780,"Amount":179,"Enabled":true,"Type":"Exchange","AmountMode":"Restock"},{"Id":18,"Group":4,"Item":12669,"Amount":1499,"Enabled":true,"Type":"Exchange","AmountMode":"Restock"},{"Id":19,"Group":4,"Item":16911,"Amount":1400,"Enabled":true,"Type":"Alchemist","Hq":true,"AmountMode":"Restock"},{"Id":4,"Group":5,"Item":41767,"Amount":150,"Enabled":true,"Type":"Exchange","AmountMode":"Restock"},{"Id":20,"Group":5,"Item":12669,"Amount":1700,"Enabled":true,"Type":"Exchange","AmountMode":"Restock"},{"Id":21,"Group":5,"Item":16911,"Amount":1700,"Enabled":true,"Type":"Alchemist","Hq":true,"AmountMode":"Restock"},{"Id":5,"Group":6,"Item":41767,"Amount":300,"Enabled":true,"Type":"Exchange","AmountMode":"Restock"},{"Id":23,"Group":6,"Item":12669,"Amount":1998,"Enabled":true,"Type":"Exchange","AmountMode":"Restock"},{"Id":24,"Group":6,"Item":16911,"Amount":1998,"Enabled":true,"Type":"Alchemist","Hq":true,"AmountMode":"Restock"},{"Id":6,"Group":7,"Item":41767,"Amount":450,"Enabled":true,"Type":"Exchange","AmountMode":"Restock"},{"Id":7,"Group":8,"Item":41767,"Amount":600,"Enabled":true,"Type":"Exchange","AmountMode":"Restock"},{"Id":8,"Group":9,"Item":41779,"Amount":18,"Enabled":true,"Type":"Exchange","AmountMode":"Restock"},{"Id":9,"Group":10,"Item":33926,"Amount":150,"Enabled":true,"Type":"Exchange","AmountMode":"Restock"},{"Id":10,"Group":11,"Item":33926,"Amount":300,"Enabled":true,"Type":"Exchange","AmountMode":"Restock"},{"Id":11,"Group":12,"Item":33926,"Amount":450,"Enabled":true,"Type":"Exchange","AmountMode":"Restock"},{"Id":12,"Group":13,"Item":33926,"Amount":512,"Enabled":true,"Type":"Exchange","AmountMode":"Restock"},{"Id":13,"Group":14,"Item":41778,"Amount":23,"Enabled":true,"Type":"Exchange","AmountMode":"Restock"},{"Id":14,"Group":15,"Item":41765,"Amount":90,"Enabled":true,"Type":"Exchange","AmountMode":"Restock"}]